dcube/__init__.py
dcube/client.py
dcube/data_pro.py
dcube/upass.py
dcube/util/__init__.py
dcube/util/protobuf/__init__.py
dcube/util/protobuf/funcs.py
dcube/util/protobuf/response_pb2.py
fzdata/__init__.py
fzdata/client.py
fzdata/data_pro.py
fzdata/upass.py
test/__init__.py
test/bar_test.py
test/billboard_test.py
test/classifying_test.py
test/dateu_test.py
test/fund_test.py
test/indictor_test.py
test/macro_test.py
test/nav_test.py
test/news_test.py
test/pro_test.py
test/ref_test.py
test/shibor_test.py
test/storing_test.py
test/trading_test.py
tushare/VERSION.txt
tushare/__init__.py
tushare/bond/__init__.py
tushare/bond/bonds.py
tushare/coins/__init__.py
tushare/coins/market.py
tushare/data/__init__.py
tushare/fund/__init__.py
tushare/fund/cons.py
tushare/fund/nav.py
tushare/futures/__init__.py
tushare/futures/cons.py
tushare/futures/domestic.py
tushare/futures/domestic_cons.py
tushare/futures/intlfutures.py
tushare/internet/__init__.py
tushare/internet/boxoffice.py
tushare/internet/caixinnews.py
tushare/internet/indexes.py
tushare/pro/__init__.py
tushare/pro/client.py
tushare/pro/data_pro.py
tushare/stock/__init__.py
tushare/stock/billboard.py
tushare/stock/classifying.py
tushare/stock/cons.py
tushare/stock/fundamental.py
tushare/stock/globals.py
tushare/stock/indictor.py
tushare/stock/macro.py
tushare/stock/macro_vars.py
tushare/stock/minsdata.py
tushare/stock/news_vars.py
tushare/stock/newsevent.py
tushare/stock/ref_vars.py
tushare/stock/reference.py
tushare/stock/shibor.py
tushare/stock/trading.py
tushare/subs/__init__.py
tushare/subs/ts_subs.py
tushare/trader/__init__.py
tushare/trader/trader.py
tushare/trader/utils.py
tushare/trader/vars.py
tushare/util/__init__.py
tushare/util/common.py
tushare/util/conns.py
tushare/util/dateu.py
tushare/util/formula.py
tushare/util/mailmerge.py
tushare/util/netbase.py
tushare/util/store.py
tushare/util/upass.py
tushare/util/vars.py
tushare/util/protobuf/__init__.py
tushare/util/protobuf/funcs.py
dcube-1.0.1.dist-info/METADATA
dcube-1.0.1.dist-info/WHEEL
dcube-1.0.1.dist-info/top_level.txt
dcube-1.0.1.dist-info/RECORD
